CHANGES.txt
LICENSE.txt
MANIFEST.in
README.md
setup.py
nearist/Client.py
nearist/Common.py
nearist/Transforms.py
nearist/__init__.py
nearist.egg-info/PKG-INFO
nearist.egg-info/SOURCES.txt
nearist.egg-info/dependency_links.txt
nearist.egg-info/requires.txt
nearist.egg-info/top_level.txt