Metadata-Version: 1.0
Name: nearist
Version: 1.0.2
Summary: Tools for Nearist hardware
Home-page: http://github.com/nearist/nearist
Author: Nearist
Author-email: nick.ryan@nearist.io
License: MIT
Platform: UNKNOWN
